[
    { "id": 1,  "value":"Health", "task":"This is a Health1","year":"Prenatal","text":"Design for young parents and all their needs.Discover a million tops, ideas and manuals Connect with people like you."},
    { "id": 1,  "value": "Health", "task":"This is a Health2" ,"year":"Prenatal","text":"Design for young parents and all their needs.Discover a million tops, ideas and manuals Connect with people like you."},
    { "id": 1,  "value": "Health", "task":"This is a Health3", "year":"3 to 12 months","text":"Design for young parents and all their needs.Discover a million tops, ideas and manuals Connect with people like you." },
    { "id": 1,  "value": "Health", "task":"This is a Health4", "year":"3 to 5 years","text":"Design for young parents and all their needs.Discover a million tops, ideas and manuals Connect with people like you." },
    { "id": 2,  "value": "Nutrition", "task":"This is a nutrition1", "year":"3 to 12 months","text":"Design for young parents and all their needs.Discover a million tops, ideas and manuals Connect with people like you." },
    { "id": 2,  "value": "Nutrition", "task":"This is a nutrition1", "year":"3 to 5 years","text":"Design for young parents and all their needs.Discover a million tops, ideas and manuals Connect with people like you." },
    { "id": 3,  "value": "Mental development", "task":"This is a mental development1", "year":"3 to 5 years","text":"Design for young parents and all their needs.Discover a million tops, ideas and manuals Connect with people like you." },
    { "id": 3,  "value": "Mental development", "task":"This is a mental development1", "year":"3 to 12 months","text":"Design for young parents and all their needs.Discover a million tops, ideas and manuals Connect with people like you." }
]